README.rst
enrich_pvalues.py
setup.py
enrich_pvalues.egg-info/PKG-INFO
enrich_pvalues.egg-info/SOURCES.txt
enrich_pvalues.egg-info/dependency_links.txt
enrich_pvalues.egg-info/entry_points.txt
enrich_pvalues.egg-info/requires.txt
enrich_pvalues.egg-info/top_level.txt