Metadata-Version: 1.1
Name: enrich-pvalues
Version: 1.0b2
Summary: Compare one dataset to another at a variety of p-value cutoffs
Home-page: https://github.com/MikeDacre/enrich_pvalues
Author: Mike Dacre
Author-email: mike.dacre@gmail.com
License: MIT
Download-URL: https://github.com/MikeDacre/enrich_pvalues/archive/v1.0b2.tar.gz
Keywords: statistics p-values biology molecular-biology console
Platform: UNKNOWN
Classifier: Development Status :: 4 - Beta
Classifier: Environment :: Console
Classifier: Intended Audience :: End Users/Desktop
Classifier: Intended Audience :: System Administrators
Classifier: License :: OSI Approved :: MIT License
Classifier: Natural Language :: English
Classifier: Operating System :: MacOS :: MacOS X
Classifier: Operating System :: POSIX
Classifier: Programming Language :: Python
Classifier: Programming Language :: Python :: 2
Classifier: Programming Language :: Python :: 3
Classifier: Topic :: Utilities
Requires: tabulate
Requires: tqdm
Requires: numpy
Requires: pandas
Requires: matplotlib
Requires: seaborn
Requires: openpyxl
Requires: xlrd
Requires: xlwt
